{
  "opt_checksum": "optional_header",
  "imp_func_hash_149": "imports_func_hash",
  "rich_max_build_id": "rich_header",
  "opt_dllchar_HIGH_ENTROPY_VA": "optional_header",
  "coff_char_DLL": "coff_header",
  "rsrc_has_version": "resources",
  "overlay_entropy": "overlay",
  "has_repro": "debug",
  "overlay_size": "overlay",
  "has_overlay": "overlay",
  "has_debug": "debug",
  "sec2_vsize": "sections_per_slot",
  "opt_imagebase": "optional_header",
  "opt_dllchar_NO_SEH": "optional_header",
  "opt_section_alignment": "optional_header",
  "imp_dll_hash_43": "imports_dll_hash",
  "sec_max_entropy": "sections_aggregate",
  "dd_CLR_RUNTIME_HEADER_rva": "data_directories",
  "opt_dllchar_DYNAMIC_BASE": "optional_header",
  "dd_CERTIFICATE_TABLE_size": "data_directories",
  "coff_char_LARGE_ADDRESS_AWARE": "coff_header",
  "sig_verified": "signatures",
  "opt_subsystem": "optional_header",
  "opt_dllchar_NX_COMPAT": "optional_header",
  "checksum_matches": "optional_header"
}